cli/__init__.py
cli/core.py
cli/main.py
cli/no_device.py
cli/per_device.py
cli/per_gpu.py
cli/per_gpu_nvswitch.py
cli/plugins/__init__.py
gpu/__init__.py
gpu/defines.py
gpu/devid_chips.py
gpu/devid_names.py
gpu/devid_properties.py
gpu/error.py
gpu/fsp_emem_rpc.py
gpu/fsp_mctp.py
gpu/fsp_mnoc_rpc.py
gpu/mnoc.py
gpu/mse.py
gpu/prc.py
gpu/properties.py
gpu/unit.py
gpu/regs/__init__.py
gpu/regs/core.py
gpu/regs/ga102/__init__.py
gpu/regs/gb100/__init__.py
gpu/regs/gb100/boot.py
gpu/regs/gb100/mnoc.py
gpu/regs/gb100/pbus.py
gpu/regs/gb100/therm.py
gpu/regs/gb100/therm_int.py
gpu/regs/gb100/top.py
gpu/regs/gb100/top_int.py
gpu/regs/gb102/__init__.py
gpu/regs/gb102/therm.py
gpu/regs/gb102/therm_int.py
gpu/regs/gb102/top.py
gpu/regs/gb102/top_int.py
gpu/regs/gb202/__init__.py
gpu/regs/gb202/boot.py
gpu/regs/gb202/therm.py
gpu/regs/gb202/therm_int.py
gpu/regs/gb202/top.py
gpu/regs/gb202/top_int.py
gpu/regs/gh100/__init__.py
gpu/regs/gh100/gfw_int.py
gpu/regs/gh100/therm.py
gpu/regs/gh100/therm_int.py
gpu/regs/gh100/top.py
gpu/units/__init__.py
gpu/units/c2c.py
gpu/units/nvlink.py
gpu/units/nvlink_ampere.py
gpu/units/nvlink_auto.py
gpu/units/nvlink_blackwell.py
gpu/units/nvlink_hopper.py
pci/__init__.py
pci/bridge.py
pci/cx7.py
pci/defines.py
pci/device.py
pci/devices.py
utils/__init__.py
utils/binaries.py
utils/bitfield.py
utils/device_field.py
utils/file_map.py
utils/file_raw.py
utils/formatted_tuple.py
utils/ints_to_bytes.py
utils/nice_struct.py
utils/platform_config.py
utils/sysfs.py
nvidia_gpu_tools.py
nvidia_gpu_admin_tools-2025.11.21.dist-info/METADATA
nvidia_gpu_admin_tools-2025.11.21.dist-info/WHEEL
nvidia_gpu_admin_tools-2025.11.21.dist-info/RECORD
