Metadata-Version: 2.4
Name: nvidia-gpu-admin-tools
Version: 2025.11.21
Summary: NVIDIA GPU administration and configuration tools for managing Confidential Computing modes and debugging
Project-URL: Homepage, https://github.com/fpolica91/gpu-admin-tools
Project-URL: Issues, https://github.com/fpolica91/gpu-admin-tools/issues
Project-URL: Repository, https://github.com/fpolica91/gpu-admin-tools.git
Author: NVIDIA CORPORATION & AFFILIATES
License: MIT
Keywords: admin,cc-mode,confidential-computing,gpu,nvidia,nvlink
Classifier: Development Status :: 4 - Beta
Classifier: Intended Audience :: Developers
Classifier: Intended Audience :: System Administrators
Classifier: License :: OSI Approved :: MIT License
Classifier: Operating System :: POSIX :: Linux
Classifier: Programming Language :: Python :: 3
Classifier: Programming Language :: Python :: 3.8
Classifier: Programming Language :: Python :: 3.9
Classifier: Programming Language :: Python :: 3.10
Classifier: Programming Language :: Python :: 3.11
Classifier: Programming Language :: Python :: 3.12
Classifier: Topic :: System :: Hardware
Classifier: Topic :: System :: Systems Administration
Requires-Python: >=3.8
Provides-Extra: dev
Requires-Dist: pytest-cov>=4.0; extra == 'dev'
Requires-Dist: pytest>=7.0; extra == 'dev'
